star_ratings/__init__.py
star_ratings/example.py
star_ratings/frontend/build/asset-manifest.json
star_ratings/frontend/build/bootstrap.min.css
star_ratings/frontend/build/index.html
star_ratings/frontend/build/static/js/main.ec585fbf.js
star_ratings/frontend/build/static/js/main.ec585fbf.js.LICENSE.txt
star_ratings/frontend/build/static/js/main.ec585fbf.js.map
streamlit_star_ratings-0.0.1.dist-info/LICENSE
streamlit_star_ratings-0.0.1.dist-info/METADATA
streamlit_star_ratings-0.0.1.dist-info/WHEEL
streamlit_star_ratings-0.0.1.dist-info/top_level.txt
streamlit_star_ratings-0.0.1.dist-info/RECORD
